ue5/__init__.py
ue5/conan.py
ue5/detector.py
ue5_tools-0.1.0.dist-info/METADATA
ue5_tools-0.1.0.dist-info/WHEEL
ue5_tools-0.1.0.dist-info/top_level.txt
ue5_tools-0.1.0.dist-info/RECORD
