Metadata-Version: 2.1
Name: ue5-tools
Version: 0.1.0
Summary: UE5 Python helper tools
Home-page: https://github.com/retroandchill/ue5-tools
Author: Retro & Chill
Requires-Dist: conan>=2.9.2
